flask_applauncher_bundle-1.14.dist-info/DESCRIPTION.rst
flask_applauncher_bundle-1.14.dist-info/METADATA
flask_applauncher_bundle-1.14.dist-info/RECORD
flask_applauncher_bundle-1.14.dist-info/WHEEL
flask_applauncher_bundle-1.14.dist-info/metadata.json
flask_applauncher_bundle-1.14.dist-info/top_level.txt
flask_bundle/__init__.py
flask_bundle/bundle.py
